pytoolkit/__init__.py
pytoolkit/cli.py
pytoolkit/rename_prefix_suffix.py
pytoolkit/rename_sequentially.py
pytoolkit/show_parent.py
pytoolkit/show_path.py
pytoolkit/utils.py
pytoolkit_leomb-0.1.0.dist-info/METADATA
pytoolkit_leomb-0.1.0.dist-info/WHEEL
pytoolkit_leomb-0.1.0.dist-info/entry_points.txt
pytoolkit_leomb-0.1.0.dist-info/licenses/LICENSE
pytoolkit_leomb-0.1.0.dist-info/RECORD
