Metadata-Version: 2.4
Name: pytoolkit-leomb
Version: 0.1.0
Summary: A collection of Python-powered CLI tools for the command line.
Author: Leonardo Modesto
License-Expression: MIT
License-File: LICENSE
Requires-Python: >=3.10
Requires-Dist: rich>=13.0.0
Requires-Dist: typer>=0.12.0
Provides-Extra: dev
Requires-Dist: pytest; extra == 'dev'
